hackycfgparser/LICENSE
hackycfgparser/README.md
hackycfgparser/__init__.py
hackycfgparser/requirements.txt
hackycfgparser/thirdparty.json
hackycfgparser-0.12.dist-info/LICENSE.rst
hackycfgparser-0.12.dist-info/METADATA
hackycfgparser-0.12.dist-info/WHEEL
hackycfgparser-0.12.dist-info/top_level.txt
hackycfgparser-0.12.dist-info/RECORD
