Metadata-Version: 2.1
Name: hackycfgparser
Version: 0.12
Summary: Hacky config parser - parses ConfigParser-compatible files / sys.argv and changes the defaults of functions
Home-page: https://github.com/hansalemaos/hackycfgparser
Author: Johannes Fischer
Author-email: aulasparticularesdealemaosp@gmail.com
License: MIT
Keywords: hacky,config,parser,decorator
Classifier: Development Status :: 4 - Beta
Classifier: Programming Language :: Python :: 3 :: Only
Classifier: Programming Language :: Python :: 3.10
Classifier: Topic :: Software Development :: Libraries :: Python Modules
Classifier: Topic :: Utilities
License-File: LICENSE.rst
Requires-Dist: deepcopyall
Requires-Dist: flatten-any-dict-iterable-or-whatsoever
Requires-Dist: tolerant-isinstance
